{
  "id": "briefing-2026-01-23",
  "slug": "briefing-2026-01-23",
  "title": "Finding Strength in Steady Choices and Smart Racing",
  "excerpt": "",
  "date": "2026-01-23",
  "category": "",
  "tags": [],
  "readTimeMinutes": 6,
  "body": "Running is as much about how you navigate change as how fast you can move. This week unfolded with reminders that the best runners are those who adjust, remain consistent, and exercise patience during transitions. These lessons reach beyond the track and trail to inform every step of training and racing.\n\nThe first theme is adapting to the unexpected. When a leading contender steps away, the race reshapes and new possibilities emerge. Similarly, in training and competition, circumstances often shift unexpectedly. Instead of clinging rigidly to plans, the most resilient runners respond with thoughtful adjustments, smoothing the path forward without losing momentum.\n\nClosely connected is the art of pacing with flexibility. Real races rarely follow a script, so being attuned to how your body feels and how conditions unfold allows you to make smarter choices. Whether during a debut half marathon or record attempts, practicing deliberate pace changes helps conserve energy and optimize performance over the long haul.\n\nConsistency stands as another pillar. Prioritizing steady effort over perfection builds a foundation that holds through a demanding season. Developing this mindset prevents burnout and helps maintain progress even when external pressures and consecutive competitions tempt runners to push too hard.\n\nPatience completes the picture. Whether returning from a long break or adapting nutrition strategies at altitude, gradual progression nurtures sustainable improvement. Impatience risks setbacks, but committed patience fosters strength and resilience that pay dividends down the road.\n\nLooking ahead, embracing these interconnected themes sets the stage for a more mindful and enduring approach to running. Next week invites a deeper dive into how to harness mental focus and recovery tactics that complement steady physical progress. The quiet power of smart, steady decisions will continue to guide the journey.",
  "keyTakeaway": "Practice adapting plans thoughtfully, embrace consistent effort over perfection, and cultivate patience to build resilience for lasting progress in running.",
  "sourceUrl": ""
}